tmcpy/__init__.py
tmcpy/client.py
tmcpy/event.py
tmcpy/message.py
tmcpy/messageio.py
tmcpy/messagetype.py
tmcpy/utils.py
tmcpy-0.3.7.dist-info/DESCRIPTION.rst
tmcpy-0.3.7.dist-info/METADATA
tmcpy-0.3.7.dist-info/metadata.json
tmcpy-0.3.7.dist-info/pbr.json
tmcpy-0.3.7.dist-info/RECORD
tmcpy-0.3.7.dist-info/top_level.txt
tmcpy-0.3.7.dist-info/WHEEL
