Metadata-Version: 2.0
Name: tmcpy
Version: 0.3.7
Summary: 淘宝平台消息服务客户端 for Python
Home-page: https://github.com/messense/tmcpy
Author: baocaixiong,messense
Author-email: baocaixiong@gmail.com,messense@icloud.com
License: MIT
Keywords: taobao tmc python
Platform: UNKNOWN
Requires-Dist: tornado (>=4.1)
Requires-Dist: six (>=1.8.0)
Requires-Dist: simplejson (>=3.5.2)
